zentra_sdk/__init__.py
zentra_sdk/cli/__init__.py
zentra_sdk/cli/builder/__init__.py
zentra_sdk/cli/builder/docker.py
zentra_sdk/cli/commands/__init__.py
zentra_sdk/cli/commands/setup.py
zentra_sdk/cli/conf/__init__.py
zentra_sdk/cli/conf/checks.py
zentra_sdk/cli/conf/logger.py
zentra_sdk/cli/constants/__init__.py
zentra_sdk/cli/constants/display.py
zentra_sdk/cli/constants/message.py
zentra_sdk/cli/main.py
zentra_sdk/cli/setup_assets/frontend/.env.local.template
zentra_sdk/cli/setup_assets/frontend/next.config.mjs
zentra_sdk/cli/setup_assets/root/.gitignore
zentra_sdk/cli/setup_assets/root/README.md
zentra_sdk-0.1.1.dist-info/LICENSE
zentra_sdk-0.1.1.dist-info/METADATA
zentra_sdk-0.1.1.dist-info/WHEEL
zentra_sdk-0.1.1.dist-info/entry_points.txt
zentra_sdk-0.1.1.dist-info/RECORD
