Metadata-Version: 2.1
Name: zentra_sdk
Version: 0.1.1
Summary: An open-source Python SDK for building FastAPI and Next.js apps faster.
Home-page: https://github.com/Achronus/zentra
License: MIT
Author: Ryan Partridge
Author-email: rpartridge101@gmail.com
Requires-Python: >=3.12,<4.0
Classifier: Development Status :: 3 - Alpha
Classifier: Environment :: Console
Classifier: Framework :: FastAPI
Classifier: Intended Audience :: Developers
Classifier: License :: OSI Approved :: MIT License
Classifier: Natural Language :: English
Classifier: Operating System :: MacOS
Classifier: Operating System :: Microsoft :: Windows
Classifier: Operating System :: POSIX :: Linux
Classifier: Programming Language :: JavaScript
Classifier: Programming Language :: Python
Classifier: Programming Language :: Python :: 3
Classifier: Programming Language :: Python :: 3.12
Classifier: Topic :: Software Development
Classifier: Topic :: Software Development :: Build Tools
Classifier: Topic :: Software Development :: Code Generators
Classifier: Topic :: Software Development :: Libraries :: Application Frameworks
Requires-Dist: docker (>=7.1.0,<8.0.0)
Requires-Dist: pydantic (>=2.8,<3.0)
Requires-Dist: typer (>=0.12,<0.13)
Requires-Dist: zentra-api (>=0.1,<0.2)
Project-URL: Repository, https://github.com/Achronus/zentra
Project-URL: issues, https://github.com/Achronus/zentra/issues
